<?xml version="1.0"?>
<troubleshoot>
    <node>
        <id>0</id>
        <parentId>-1</parentId>
        <header>Root Node</header>
        <description>Root Page - desctription text.</description>
        <isExecuteProcess>false</isExecuteProcess> 
        <actionCode></actionCode>
        <imageLink>Resources\troubleshooting.png</imageLink>
        <videoLink></videoLink>
        <children>
            <node>
                <id>1</id>
                <parentId>0</parentId>
                <header>Check Solvent Bottles</header>
                <description>If the solvent bottles are not empty, please contact RheoSense for assistance.  (service@rheosense.com, 925.866.3801x2)  Otherwise, please inspect the solvent bottles and press 'Next'.</description>
                <isExecuteProcess>false</isExecuteProcess> 
                <actionCode></actionCode>
                <imageLink>Resources\initium.JPG</imageLink>
                <videoLink></videoLink>
                <children>     
                    <node>
                        <id>1000</id>
                        <parentId>1</parentId>
                        <header>Refill Solvents</header>
                        <description>Follow the instructions in manual to refill solvents, then press 'Next' to peform the leak test.</description>
                        <isExecuteProcess>false</isExecuteProcess> 
                        <actionCode></actionCode>
                        <imageLink>Resources\solventBottles.JPG</imageLink>
                        <videoLink></videoLink>
                        <pdfLink></pdfLink>
                        <children>     
                            <node>
                                <id>1001</id>
                                <parentId>1000</parentId>
                                <header>Running Leak Test</header>
                                <description>Please wait.</description>
                                <isExecuteProcess>true</isExecuteProcess>
                                <actionCode>0</actionCode>
                                <imageLink></imageLink>
                                <videoLink></videoLink>
                                <children>     
                                    <node>
                                        <id>1002</id>
                                        <parentId>1001</parentId>
                                        <header>Passed Leak Test</header>
                                        <description>Proceed to the next step in the diagnostic test or start of job.</description>
                                        <isExecuteProcess>false</isExecuteProcess> 
                                        <actionCode></actionCode>
                                        <imageLink></imageLink>
                                        <videoLink></videoLink>
                                        <children>                                                                        
                                        </children>
                                    </node>
                                    <node>                                        
                                        <id>1006</id>
                                        <parentId>1001</parentId>
                                        <header>Failed Leak Test</header>
                                        <description>Please tighten the fittings on the syringe and press 'Next' to run the leak test again.</description>
                                        <isExecuteProcess>false</isExecuteProcess> 
                                        <actionCode></actionCode>
                                        <imageLink>Resources\testSyringeAssembly.JPG</imageLink>
                                        <videoLink></videoLink>
                                        <children>          
                                            <node>
                                                <id>1007</id>
                                                <parentId>1006</parentId>
                                                <header>Running Leak Test</header>
                                                <description>Please wait.</description>
                                                <isExecuteProcess>true</isExecuteProcess>
                                                <actionCode>0</actionCode>
                                                <imageLink></imageLink>
                                                <videoLink></videoLink>
                                                <children> 
                                                    <node>
                                                        <id>1008</id>
                                                        <parentId>1007</parentId>
                                                        <header>Passed</header>
                                                        <description>Proceed to the next step in the diagnostic test or start of job.</description>
                                                        <isExecuteProcess>false</isExecuteProcess> 
                                                        <actionCode></actionCode>
                                                        <imageLink></imageLink>
                                                        <videoLink></videoLink>
                                                        <children>           
                                                        </children>
                                                    </node> 
                                                    <node>
                                                        <id>1010</id>
                                                        <parentId>1007</parentId>
                                                        <header>Failed</header>
                                                        <description>Contact RheoSense for assistance.  (service@rheosense.com, 925.866.3801x2)</description>
                                                        <isExecuteProcess>false</isExecuteProcess>
                                                        <actionCode></actionCode>
                                                        <imageLink></imageLink>
                                                        <videoLink></videoLink>
                                                        <children>                                                                                 
                                                        </children>
                                                    </node>   
                                                </children>
                                            </node>    
                                        </children>
                                    </node>    
                                </children>
                            </node>   
                        </children>
                    </node>           
                </children>
            </node>
        </children>
     </node>
</troubleshoot>